{"success":true,"season":"spring","year":2026,"channel":"all","startDate":"2026-02-01","endDate":"2026-05-31","isPartial":false,"label":"Spring 2026","revenueSource":"mixed","sourceCounts":{"fishbowl":100,"db":4,"csv":0,"none":0},"summary":{"totalSkus":104,"pricedSkus":104,"unpricedSkus":0,"totalRevenue":1138179.8,"totalCost":412237.37,"totalMargin":725942.43,"avgMarginPct":0.6378099751902112,"totalUnits":34945,"totalLbs":212816,"tierCounts":{"A":36,"B":28,"C":40},"newSkuCount":104,"negativeMarginCount":0,"costCoveragePct":0.9615384615384616},"rows":[{"sku":"S-DUTCH-5-LB","productName":"White Dutch Clover Seeds - 5 lbs","category":"Lawn Alt","units":1249,"lbs":6245,"orders":239,"unitPrice":40.43,"revenue":50491.51,"unitCost":21.5,"totalCost":26853.5,"margin":23638.01,"marginPct":0.4681581121261772,"isNewSku":true,"hasPrice":true,"source":"fishbowl","costSource":"fishbowl","revenuePct":0.04436162897988522,"cumulativeRevenuePct":0.04436162897988522,"tier":"A"},{"sku":"TURF-CLV-5-LB","productName":"Lawn Alternative clover mix","category":"Lawn Alt","units":2807,"lbs":14035,"orders":416,"unitPrice":17.9,"revenue":50257.28,"unitCost":7.21,"totalCost":20247.07,"margin":30010.21,"marginPct":0.5971315996408878,"isNewSku":true,"hasPrice":true,"source":"fishbowl","costSource":"fishbowl","revenuePct":0.04415583548398941,"cumulativeRevenuePct":0.08851746446387462,"tier":"A"},{"sku":"PB-CHIX-5-LB","productName":"Chicken Forage Mix","category":"Pasture","units":2595,"lbs":12975,"orders":373,"unitPrice":19.01,"revenue":49321.83,"unitCost":8.76,"totalCost":22737.3,"margin":26584.53,"marginPct":0.5390012900981167,"isNewSku":true,"hasPrice":true,"source":"fishbowl","costSource":"fishbowl","revenuePct":0.04333395303624258,"cumulativeRevenuePct":0.1318514175001172,"tier":"A"},{"sku":"PB-COW-NTR-10-LB","productName":"Northern/Transitional Dairy Cow & Cattle Forage Mix","category":"Pasture","units":1346,"lbs":13460,"orders":63,"unitPrice":31.69,"revenue":42654.96,"unitCost":16.63,"totalCost":22381.51,"margin":20273.45,"marginPct":0.4752893919019031,"isNewSku":true,"hasPrice":true,"source":"fishbowl","costSource":"fishbowl","revenuePct":0.037476469007796456,"cumulativeRevenuePct":0.16932788650791364,"tier":"A"},{"sku":"PB-COW-SO-10-LB","productName":"Southern Dairy Cow & Cattle Forage Mix","category":"Pasture","units":1245,"lbs":12450,"orders":55,"unitPrice":32.53,"revenue":40499.77,"unitCost":17.18,"totalCost":21386.61,"margin":19113.16,"marginPct":0.4719325566540255,"isNewSku":true,"hasPrice":true,"source":"fishbowl","costSource":"fishbowl","revenuePct":0.035582928110303814,"cumulativeRevenuePct":0.20491081461821745,"tier":"A"},{"sku":"TURF-W-TALL-5-LB","productName":"TWCA Water-Wise Triple-Play Turf Blend","category":"Turf","units":1343,"lbs":6715,"orders":128,"unitPrice":29.55,"revenue":39682.28,"unitCost":5.48,"totalCost":7364.86,"margin":32317.42,"marginPct":0.8144043134618273,"isNewSku":true,"hasPrice":true,"source":"fishbowl","costSource":"fishbowl","revenuePct":0.034864684823961885,"cumulativeRevenuePct":0.23977549944217932,"tier":"A"},{"sku":"TURF-BUDA-3-LB","productName":"Sundancer Buffalo Grass","category":"Turf","units":378,"lbs":1134,"orders":69,"unitPrice":102.42,"revenue":38713.16,"unitCost":31.03,"totalCost":11728.53,"margin":26984.63,"marginPct":0.6970402312805257,"isNewSku":true,"hasPrice":true,"source":"fishbowl","costSource":"fishbowl","revenuePct":0.034013220055390175,"cumulativeRevenuePct":0.2737887194975695,"tier":"A"},{"sku":"PB-HRSE-TR-10-LB","productName":"Transitional Horse Forage Mix","category":"Pasture","units":867,"lbs":8670,"orders":45,"unitPrice":41.14,"revenue":35668.64,"unitCost":13.51,"totalCost":11711.33,"margin":23957.31,"marginPct":0.6716631191993864,"isNewSku":true,"hasPrice":true,"source":"fishbowl","costSource":"fishbowl","revenuePct":0.031338317548773906,"cumulativeRevenuePct":0.3051270370463434,"tier":"A"},{"sku":"TURF-W-BR-5-LB","productName":"TWCA Water-Wise Blue Ribbon Mix","category":"Turf","units":1038,"lbs":5190,"orders":137,"unitPrice":34.2,"revenue":35500.65,"unitCost":11.09,"totalCost":11510.99,"margin":23989.66,"marginPct":0.6757526974858207,"isNewSku":true,"hasPrice":true,"source":"fishbowl","costSource":"fishbowl","revenuePct":0.031190722239140052,"cumulativeRevenuePct":0.33631775928548346,"tier":"A"},{"sku":"TURF-FINE-5-LB","productName":"Fine Fescue Turf Mix","category":"Turf","units":1126,"lbs":5630,"orders":187,"unitPrice":31.51,"revenue":35483.56,"unitCost":10.58,"totalCost":11912.62,"margin":23570.94,"marginPct":0.6642777669433394,"isNewSku":true,"hasPrice":true,"source":"fishbowl","costSource":"fishbowl","revenuePct":0.0311757070367968,"cumulativeRevenuePct":0.36749346632228025,"tier":"A"},{"sku":"PB-GRSC-10-LB","productName":"Green Screen Food Plot","category":"Food Plot","units":1075,"lbs":10750,"orders":271,"unitPrice":32.45,"revenue":34882.51,"unitCost":10.9,"totalCost":11716.44,"margin":23166.07,"marginPct":0.6641170603835561,"isNewSku":true,"hasPrice":true,"source":"fishbowl","costSource":"fishbowl","revenuePct":0.030647627026942473,"cumulativeRevenuePct":0.3981410933492227,"tier":"A"},{"sku":"PB-HRSE-SO-10-LB","productName":"Southern Horse Forage Mix","category":"Pasture","units":958,"lbs":9580,"orders":49,"unitPrice":32.93,"revenue":31547.14,"unitCost":14.72,"totalCost":14097.8,"margin":17449.34,"marginPct":0.5531195537852243,"isNewSku":true,"hasPrice":true,"source":"fishbowl","costSource":"fishbowl","revenuePct":0.027717184929832685,"cumulativeRevenuePct":0.42585827827905537,"tier":"A"},{"sku":"TURF-WSHD-5-LB","productName":"TWCA Water-Wise Shade Mix","category":"Turf","units":865,"lbs":4325,"orders":183,"unitPrice":35.45,"revenue":30665.2,"unitCost":6.88,"totalCost":5955,"margin":24710.2,"marginPct":0.8058059298488188,"isNewSku":true,"hasPrice":true,"source":"fishbowl","costSource":"fishbowl","revenuePct":0.026942316143723496,"cumulativeRevenuePct":0.45280059442277887,"tier":"A"},{"sku":"S-RICE-5-LB","productName":"Rice Hulls - 5lbs","category":"Planting Aide","units":1409,"lbs":7045,"orders":259,"unitPrice":21.59,"revenue":30423.38,"unitCost":1.27,"totalCost":1787.59,"margin":28635.79,"marginPct":0.9412428862276315,"isNewSku":true,"hasPrice":true,"source":"fishbowl","costSource":"fishbowl","revenuePct":0.026729854105651832,"cumulativeRevenuePct":0.4795304485284307,"tier":"A"},{"sku":"PB-HRSE-N-10-LB","productName":"Northern Horse Forage Mix","category":"Pasture","units":1119,"lbs":11190,"orders":92,"unitPrice":24.2,"revenue":27076.73,"unitCost":16.21,"totalCost":18138.25,"margin":8938.48,"marginPct":0.33011667213877005,"isNewSku":true,"hasPrice":true,"source":"fishbowl","costSource":"fishbowl","revenuePct":0.023789501447838014,"cumulativeRevenuePct":0.5033199499762687,"tier":"A"},{"sku":"PB-GAME-10-LB","productName":"Big Game Forage Mix","category":"Food Plot","units":886,"lbs":8860,"orders":95,"unitPrice":25.63,"revenue":22710.82,"unitCost":10.14,"totalCost":8983.86,"margin":13726.96,"marginPct":0.6044237944732951,"isNewSku":true,"hasPrice":true,"source":"fishbowl","costSource":"fishbowl","revenuePct":0.019953631227684752,"cumulativeRevenuePct":0.5232735812039535,"tier":"A"},{"sku":"PG-TRRE-5-LB","productName":"White Clover (Pasture Type)","category":"Pasture","units":670,"lbs":3350,"orders":176,"unitPrice":33.07,"revenue":22159.15,"unitCost":19,"totalCost":12729.39,"margin":9429.76,"marginPct":0.4255470087977201,"isNewSku":true,"hasPrice":true,"source":"fishbowl","costSource":"fishbowl","revenuePct":0.019468936278784765,"cumulativeRevenuePct":0.5427425174827383,"tier":"A"},{"sku":"SUSTANE-4-6-4","productName":"Organic Seed Starter Fertilizer 4-6-4","category":"Planting Aide","units":188,"lbs":7520,"orders":69,"unitPrice":107.91,"revenue":20286.68,"unitCost":24.91,"totalCost":4682.73,"margin":15603.95,"marginPct":0.7691721858874888,"isNewSku":true,"hasPrice":true,"source":"fishbowl","costSource":"fishbowl","revenuePct":0.017823791987873962,"cumulativeRevenuePct":0.5605663094706123,"tier":"A"},{"sku":"S-RICE-45-LB","productName":"Rice Hulls","category":"Planting Aide","units":192,"lbs":8640,"orders":35,"unitPrice":104.27,"revenue":20020.53,"unitCost":11.36,"totalCost":2181.09,"margin":17839.44,"marginPct":0.8910573296511132,"isNewSku":true,"hasPrice":true,"source":"fishbowl","costSource":"fishbowl","revenuePct":0.01758995371381568,"cumulativeRevenuePct":0.5781562631844279,"tier":"A"},{"sku":"WB-CALN-0.5-LB","productName":"California Native Wildflower Mix","category":"CA Collection","units":452,"lbs":226,"orders":43,"unitPrice":42.89,"revenue":19386.3,"unitCost":7.25,"totalCost":3275.36,"margin":16110.94,"marginPct":0.8310476986325396,"isNewSku":true,"hasPrice":true,"source":"fishbowl","costSource":"fishbowl","revenuePct":0.017032721895081943,"cumulativeRevenuePct":0.5951889850795099,"tier":"A"},{"sku":"S-MICRO-1-LB","productName":"Microclover","category":"Lawn Alt","units":488,"lbs":488,"orders":91,"unitPrice":38.94,"revenue":19001.6,"unitCost":14.57,"totalCost":7110.16,"margin":11891.44,"marginPct":0.6258125631525767,"isNewSku":true,"hasPrice":true,"source":"fishbowl","costSource":"fishbowl","revenuePct":0.01669472608809257,"cumulativeRevenuePct":0.6118837111676024,"tier":"A"},{"sku":"TURF-W-BLUE-5-LB","productName":"TWCA Water-Wise Bluegrass Turf Blend","category":"Turf","units":273,"lbs":1365,"orders":35,"unitPrice":68.53,"revenue":18709.74,"unitCost":12.89,"totalCost":3517.71,"margin":15192.03,"marginPct":0.8119850943946842,"isNewSku":true,"hasPrice":true,"source":"fishbowl","costSource":"fishbowl","revenuePct":0.016438299115833888,"cumulativeRevenuePct":0.6283220102834364,"tier":"A"},{"sku":"PB-ALPACA-10-LB","productName":"Alpaca/Llama Pasture Mix","category":"Pasture","units":765,"lbs":7650,"orders":70,"unitPrice":24.18,"revenue":18496.78,"unitCost":17.46,"totalCost":13360.43,"margin":5136.35,"marginPct":0.2776888734147241,"isNewSku":true,"hasPrice":true,"source":"fishbowl","costSource":"fishbowl","revenuePct":0.016251193352754975,"cumulativeRevenuePct":0.6445732036361913,"tier":"A"},{"sku":"PB-HONEY-5-LB","productName":"Honey Bee Pasture Mix","category":"Pasture","units":382,"lbs":1910,"orders":34,"unitPrice":47.66,"revenue":18206.41,"unitCost":30.07,"totalCost":11485.92,"margin":6720.49,"marginPct":0.3691276863478302,"isNewSku":true,"hasPrice":true,"source":"fishbowl","costSource":"fishbowl","revenuePct":0.01599607548824886,"cumulativeRevenuePct":0.6605692791244402,"tier":"A"},{"sku":"TURF-JBR-5-LB","productName":"Jimmy's Blue Ribbon Premium Grass Seed Mix - 5 LB","category":"Turf","units":227,"lbs":1135,"orders":57,"unitPrice":78.27,"revenue":17766.66,"unitCost":11.2,"totalCost":2542.44,"margin":15224.22,"marginPct":0.856898257747939,"isNewSku":true,"hasPrice":true,"source":"fishbowl","costSource":"fishbowl","revenuePct":0.01560971298207892,"cumulativeRevenuePct":0.6761789921065191,"tier":"A"},{"sku":"WB-RM-0.5-LB","productName":"Rocky Mountain Wildflower Blend","category":"Wildflowers","units":1008,"lbs":504,"orders":92,"unitPrice":17.39,"revenue":17534.14,"unitCost":7.22,"totalCost":7279.85,"margin":10254.29,"marginPct":0.5848185311626348,"isNewSku":true,"hasPrice":true,"source":"fishbowl","costSource":"fishbowl","revenuePct":0.015405421885013235,"cumulativeRevenuePct":0.6915844139915324,"tier":"A"},{"sku":"TURF-TXN-5-LB","productName":"Texas Native Lawn Mix","category":"TX Collection","units":122,"lbs":610,"orders":38,"unitPrice":143.7,"revenue":17531.52,"unitCost":77.07,"totalCost":9402.83,"margin":8128.69,"marginPct":0.4636614509181177,"isNewSku":true,"hasPrice":true,"source":"fishbowl","costSource":"fishbowl","revenuePct":0.015403119963998648,"cumulativeRevenuePct":0.706987533955531,"tier":"A"},{"sku":"PG-DAGL-5-LB","productName":"Orchardgrass","category":"Pasture","units":542,"lbs":2710,"orders":42,"unitPrice":30.85,"revenue":16720.34,"unitCost":10.66,"totalCost":5780.34,"margin":10940,"marginPct":0.6542929150962241,"isNewSku":true,"hasPrice":true,"source":"fishbowl","costSource":"fishbowl","revenuePct":0.014690420617199487,"cumulativeRevenuePct":0.7216779545727305,"tier":"A"},{"sku":"PB-GOAT-TR-10-LB","productName":"Transitional Goat Forage Mix","category":"Pasture","units":336,"lbs":3360,"orders":137,"unitPrice":41.75,"revenue":14028.98,"unitCost":0,"totalCost":0,"margin":14028.98,"marginPct":1,"isNewSku":true,"hasPrice":true,"source":"db","costSource":"none","revenuePct":0.012325803005816822,"cumulativeRevenuePct":0.7340037575785474,"tier":"A"},{"sku":"TURF-W-SS-5-LB","productName":"TWCA Water-Wise Sun & Shade Turf Mix","category":"Turf","units":418,"lbs":2090,"orders":61,"unitPrice":32.63,"revenue":13637.89,"unitCost":9.64,"totalCost":4029.11,"margin":9608.78,"marginPct":0.7045650023574028,"isNewSku":true,"hasPrice":true,"source":"fishbowl","costSource":"fishbowl","revenuePct":0.011982192971620117,"cumulativeRevenuePct":0.7459859505501675,"tier":"A"},{"sku":"PB-TXPR-10-LB","productName":"Texas Native Prairie Mix","category":"TX Collection","units":69,"lbs":690,"orders":10,"unitPrice":179.02,"revenue":12352.07,"unitCost":123.6,"totalCost":8528.73,"margin":3823.34,"marginPct":0.3095303054467794,"isNewSku":true,"hasPrice":true,"source":"fishbowl","costSource":"fishbowl","revenuePct":0.01085247691094148,"cumulativeRevenuePct":0.756838427461109,"tier":"A"},{"sku":"PB-DRY-10-LB","productName":"Dryland Pasture Mix","category":"Pasture","units":257,"lbs":2570,"orders":16,"unitPrice":46.85,"revenue":12039.97,"unitCost":20.07,"totalCost":5157.5,"margin":6882.47,"marginPct":0.5716351452702956,"isNewSku":true,"hasPrice":true,"source":"fishbowl","costSource":"fishbowl","revenuePct":0.010578267159547192,"cumulativeRevenuePct":0.7674166946206562,"tier":"A"},{"sku":"PG-MESA-5-LB","productName":"Alfalfa","category":"Pasture","units":347,"lbs":1735,"orders":38,"unitPrice":34.32,"revenue":11908.51,"unitCost":10.25,"totalCost":3557.54,"margin":8350.97,"marginPct":0.7012606950827601,"isNewSku":true,"hasPrice":true,"source":"fishbowl","costSource":"fishbowl","revenuePct":0.010462766954746511,"cumulativeRevenuePct":0.7778794615754027,"tier":"A"},{"sku":"PB-PIG-10-LB","productName":"Pasture Pig Mix","category":"Pasture","units":284,"lbs":2840,"orders":32,"unitPrice":38.7,"revenue":10990.95,"unitCost":25.39,"totalCost":7210.2,"margin":3780.75,"marginPct":0.34398755339620324,"isNewSku":true,"hasPrice":true,"source":"fishbowl","costSource":"fishbowl","revenuePct":0.009656602585988605,"cumulativeRevenuePct":0.7875360641613913,"tier":"A"},{"sku":"PB-SGPR-10-LB","productName":"Shortgrass Prairie Mix","category":"Pasture","units":88,"lbs":880,"orders":13,"unitPrice":123.02,"revenue":10825.88,"unitCost":66.22,"totalCost":5827.37,"margin":4998.51,"marginPct":0.4617185854637222,"isNewSku":true,"hasPrice":true,"source":"fishbowl","costSource":"fishbowl","revenuePct":0.009511572776111464,"cumulativeRevenuePct":0.7970476369375028,"tier":"A"},{"sku":"WB-DR-0.5-LB","productName":"Deer Resistant Wildflower Blend","category":"Wildflowers","units":597,"lbs":298.5,"orders":43,"unitPrice":17.03,"revenue":10167.72,"unitCost":4.34,"totalCost":2593.54,"margin":7574.18,"marginPct":0.7449241324505397,"isNewSku":true,"hasPrice":true,"source":"fishbowl","costSource":"fishbowl","revenuePct":0.00893331615971395,"cumulativeRevenuePct":0.8059809530972167,"tier":"A"},{"sku":"TURF-FLN-5-LB","productName":"Florida Native Lawn Alternative Mix","category":"FL Collection","units":172,"lbs":860,"orders":69,"unitPrice":58.6,"revenue":10079.4,"unitCost":19.21,"totalCost":3304.47,"margin":6774.93,"marginPct":0.6721560807190905,"isNewSku":true,"hasPrice":true,"source":"fishbowl","costSource":"fishbowl","revenuePct":0.008855718578031338,"cumulativeRevenuePct":0.8148366716752481,"tier":"B"},{"sku":"PG-PHPR-5-LB","productName":"Timothy","category":"Pasture","units":304,"lbs":1520,"orders":24,"unitPrice":30.63,"revenue":9310.41,"unitCost":5.31,"totalCost":1613.4,"margin":7697.01,"marginPct":0.8267101019181755,"isNewSku":true,"hasPrice":true,"source":"fishbowl","costSource":"fishbowl","revenuePct":0.008180087188333508,"cumulativeRevenuePct":0.8230167588635816,"tier":"B"},{"sku":"S-FEOV-5-LB","productName":"Sheep Fescue","category":"Lawn Alt","units":276,"lbs":1380,"orders":43,"unitPrice":31.3,"revenue":8639.49,"unitCost":13.14,"totalCost":3627.45,"margin":5012.04,"marginPct":0.5801314660934846,"isNewSku":true,"hasPrice":true,"source":"fishbowl","costSource":"fishbowl","revenuePct":0.0075906196894374636,"cumulativeRevenuePct":0.830607378553019,"tier":"B"},{"sku":"TURF-BERM-5-LB","productName":"Bermuda grass Turf Blend","category":"Turf","units":78,"lbs":390,"orders":14,"unitPrice":108.86,"revenue":8491.12,"unitCost":35,"totalCost":2730,"margin":5761.12,"marginPct":0.6784876435617444,"isNewSku":true,"hasPrice":true,"source":"fishbowl","costSource":"fishbowl","revenuePct":0.007460262429538809,"cumulativeRevenuePct":0.8380676409825578,"tier":"B"},{"sku":"S-INNOC-5-LB","productName":"Am 120 Standard Mycorrhizal Inoculant","category":"Planting Aide","units":104,"lbs":520,"orders":22,"unitPrice":72.86,"revenue":7577.75,"unitCost":26,"totalCost":2704,"margin":4873.75,"marginPct":0.6431658473821384,"isNewSku":true,"hasPrice":true,"source":"fishbowl","costSource":"fishbowl","revenuePct":0.006657779377212629,"cumulativeRevenuePct":0.8447254203597705,"tier":"B"},{"sku":"TURF-HLB-5-LB","productName":"Hardy Lawn Blend","category":"Turf","units":191,"lbs":955,"orders":24,"unitPrice":38.98,"revenue":7445.14,"unitCost":17.75,"totalCost":3391.14,"margin":4054,"marginPct":0.5445162884781213,"isNewSku":true,"hasPrice":true,"source":"fishbowl","costSource":"fishbowl","revenuePct":0.006541268787233788,"cumulativeRevenuePct":0.8512666891470043,"tier":"B"},{"sku":"WB-TXPB-0.5-LB","productName":"Texas Pollinator Wildflower Mix","category":"TX Collection","units":260,"lbs":130,"orders":38,"unitPrice":27.82,"revenue":7232.73,"unitCost":11.93,"totalCost":3101.1,"margin":4131.63,"marginPct":0.5712407348262689,"isNewSku":true,"hasPrice":true,"source":"fishbowl","costSource":"fishbowl","revenuePct":0.006354646251848781,"cumulativeRevenuePct":0.8576213353988531,"tier":"B"},{"sku":"WB-AN-0.5-LB","productName":"Annual Wildflower Blend","category":"Wildflowers","units":322,"lbs":161,"orders":50,"unitPrice":21.59,"revenue":6950.67,"unitCost":5.21,"totalCost":1678.65,"margin":5272.02,"marginPct":0.7584909080707328,"isNewSku":true,"hasPrice":true,"source":"fishbowl","costSource":"fishbowl","revenuePct":0.006106829518499621,"cumulativeRevenuePct":0.8637281649173527,"tier":"B"},{"sku":"PG-FEAR2-5-LB","productName":"Tall Fescue - Pasture Type","category":"Pasture","units":233,"lbs":1165,"orders":19,"unitPrice":29.12,"revenue":6784.56,"unitCost":3.99,"totalCost":929.03,"margin":5855.53,"marginPct":0.8630670227693468,"isNewSku":true,"hasPrice":true,"source":"fishbowl","costSource":"fishbowl","revenuePct":0.005960885968983105,"cumulativeRevenuePct":0.8696890508863359,"tier":"B"},{"sku":"WB-SD-0.5-LB","productName":"Sonoran Desert Wildflower Mix","category":"Wildflowers","units":332,"lbs":166,"orders":28,"unitPrice":20.13,"revenue":6684.61,"unitCost":7.09,"totalCost":2354.75,"margin":4329.86,"marginPct":0.6477356195799007,"isNewSku":true,"hasPrice":true,"source":"fishbowl","costSource":"fishbowl","revenuePct":0.005873070318063978,"cumulativeRevenuePct":0.8755621212043998,"tier":"B"},{"sku":"PG-LOPE-5-LB","productName":"Perennial Ryegrass","category":"Pasture","units":224,"lbs":1120,"orders":20,"unitPrice":29.43,"revenue":6592.23,"unitCost":5.39,"totalCost":1207.28,"margin":5384.95,"marginPct":0.816863185902191,"isNewSku":true,"hasPrice":true,"source":"fishbowl","costSource":"fishbowl","revenuePct":0.0057919056374045605,"cumulativeRevenuePct":0.8813540268418044,"tier":"B"},{"sku":"TURF-MLB-5-LB","productName":"Meadow Lawn Blend","category":"Turf","units":251,"lbs":1255,"orders":24,"unitPrice":26.15,"revenue":6562.49,"unitCost":12.83,"totalCost":3220.18,"margin":3342.31,"marginPct":0.5093051570364298,"isNewSku":true,"hasPrice":true,"source":"fishbowl","costSource":"fishbowl","revenuePct":0.005765776198101561,"cumulativeRevenuePct":0.887119803039906,"tier":"B"},{"sku":"TURF-NFF-5-LB","productName":"Native Fine Fescue Mix","category":"Turf","units":35,"lbs":175,"orders":6,"unitPrice":182.89,"revenue":6401.32,"unitCost":47.62,"totalCost":1666.78,"margin":4734.54,"marginPct":0.7396193285134941,"isNewSku":true,"hasPrice":true,"source":"fishbowl","costSource":"fishbowl","revenuePct":0.005624172911872092,"cumulativeRevenuePct":0.8927439759517781,"tier":"B"},{"sku":"PG-POPR-5-LB","productName":"Kentucky Bluegrass (Pasture-Type)","category":"Pasture","units":203,"lbs":1015,"orders":13,"unitPrice":30.88,"revenue":6268.61,"unitCost":8.26,"totalCost":1676.29,"margin":4592.32,"marginPct":0.7325898404909541,"isNewSku":true,"hasPrice":true,"source":"fishbowl","costSource":"fishbowl","revenuePct":0.005507574462312541,"cumulativeRevenuePct":0.8982515504140907,"tier":"B"},{"sku":"WB-CCN-0.5-LB","productName":"California Coastal Native Wildflower Mix","category":"CA Collection","units":188,"lbs":94,"orders":28,"unitPrice":32.57,"revenue":6123.53,"unitCost":9.39,"totalCost":1765.45,"margin":4358.08,"marginPct":0.7116940718833745,"isNewSku":true,"hasPrice":true,"source":"fishbowl","costSource":"fishbowl","revenuePct":0.0053801077826192275,"cumulativeRevenuePct":0.9036316581967099,"tier":"B"},{"sku":"W-ESCA-0.25-LB","productName":"California Poppy","category":"CA Collection","units":700,"lbs":175,"orders":64,"unitPrice":8.68,"revenue":6074.08,"unitCost":2.97,"totalCost":2082.05,"margin":3992.03,"marginPct":0.6572238100255512,"isNewSku":true,"hasPrice":true,"source":"fishbowl","costSource":"fishbowl","revenuePct":0.0053366612199583895,"cumulativeRevenuePct":0.9089683194166682,"tier":"B"},{"sku":"PG-TRPR-5-LB","productName":"Red Clover","category":"Lawn Alt","units":244,"lbs":1220,"orders":49,"unitPrice":23.28,"revenue":5680.25,"unitCost":9.01,"totalCost":2197.94,"margin":3482.31,"marginPct":0.6130557633906958,"isNewSku":true,"hasPrice":true,"source":"fishbowl","costSource":"fishbowl","revenuePct":0.004990643833250244,"cumulativeRevenuePct":0.9139589632499184,"tier":"B"},{"sku":"CV-CNEC-5-LB","productName":"California Erosion Control Mix","category":"CA Collection","units":35,"lbs":175,"orders":8,"unitPrice":153.68,"revenue":5378.76,"unitCost":58.93,"totalCost":2062.72,"margin":3316.04,"marginPct":0.6165064066810938,"isNewSku":true,"hasPrice":true,"source":"fishbowl","costSource":"fishbowl","revenuePct":0.004725755983369233,"cumulativeRevenuePct":0.9186847192332876,"tier":"B"},{"sku":"PB-SHEP-TR-10-LB","productName":"Transitional Sheep Forage Mix","category":"Pasture","units":158,"lbs":1580,"orders":41,"unitPrice":32.55,"revenue":5143.52,"unitCost":0,"totalCost":0,"margin":5143.52,"marginPct":1,"isNewSku":true,"hasPrice":true,"source":"db","costSource":"none","revenuePct":0.004519075105708252,"cumulativeRevenuePct":0.9232037943389959,"tier":"B"},{"sku":"S-TACKI-50-LB","productName":"M-Binder Tackifier-Soil Stabilizer","category":"Planting Aide","units":43,"lbs":2150,"orders":18,"unitPrice":118.32,"revenue":5087.57,"unitCost":28.51,"totalCost":1226.11,"margin":3861.46,"marginPct":0.7589988933813197,"isNewSku":true,"hasPrice":true,"source":"fishbowl","costSource":"fishbowl","revenuePct":0.0044699176703012974,"cumulativeRevenuePct":0.9276737120092972,"tier":"B"},{"sku":"TURF-W-RYE-5-LB","productName":"TWCA Water-Wise Perennial Ryegrass","category":"Turf","units":102,"lbs":510,"orders":16,"unitPrice":42.58,"revenue":4343,"unitCost":6.18,"totalCost":630.86,"margin":3712.14,"marginPct":0.8547409624683399,"isNewSku":true,"hasPrice":true,"source":"fishbowl","costSource":"fishbowl","revenuePct":0.0038157415902127212,"cumulativeRevenuePct":0.9314894535995099,"tier":"B"},{"sku":"WB-XCVP-0.5-LB","productName":"Xerces Central Valley Pollinator Mix","category":"CA Collection","units":83,"lbs":41.5,"orders":7,"unitPrice":47.09,"revenue":3908.73,"unitCost":10.3,"totalCost":855.2,"margin":3053.53,"marginPct":0.7812077068510744,"isNewSku":true,"hasPrice":true,"source":"fishbowl","costSource":"fishbowl","revenuePct":0.003434193789065662,"cumulativeRevenuePct":0.9349236473885755,"tier":"B"},{"sku":"CV-CNFW-5-LB","productName":"California Native Fire-Wise Mix","category":"CA Collection","units":15,"lbs":75,"orders":1,"unitPrice":228.81,"revenue":3432.15,"unitCost":72.21,"totalCost":1083.21,"margin":2348.94,"marginPct":0.6843931646344128,"isNewSku":true,"hasPrice":true,"source":"fishbowl","costSource":"fishbowl","revenuePct":0.003015472599320422,"cumulativeRevenuePct":0.9379391199878959,"tier":"B"},{"sku":"PG-PAVI-5-LB","productName":"Switchgrass","category":"Pasture","units":40,"lbs":200,"orders":11,"unitPrice":83.64,"revenue":3345.43,"unitCost":9.71,"totalCost":388.34,"margin":2957.09,"marginPct":0.8839192570162879,"isNewSku":true,"hasPrice":true,"source":"fishbowl","costSource":"fishbowl","revenuePct":0.0029392807709291606,"cumulativeRevenuePct":0.9408784007588251,"tier":"B"},{"sku":"PG-BUDA-5-LB","productName":"Buffalograss","category":"Pasture","units":11,"lbs":55,"orders":6,"unitPrice":291.81,"revenue":3209.89,"unitCost":84.35,"totalCost":927.82,"margin":2282.07,"marginPct":0.7109495964036151,"isNewSku":true,"hasPrice":true,"source":"fishbowl","costSource":"fishbowl","revenuePct":0.0028201958952355313,"cumulativeRevenuePct":0.9436985966540606,"tier":"B"},{"sku":"PG-SECE-5-LB","productName":"Cereal Rye","category":"Pasture","units":136,"lbs":680,"orders":11,"unitPrice":23.35,"revenue":3175.77,"unitCost":1.53,"totalCost":207.61,"margin":2968.16,"marginPct":0.9346268778910312,"isNewSku":true,"hasPrice":true,"source":"fishbowl","costSource":"fishbowl","revenuePct":0.0027902182062974567,"cumulativeRevenuePct":0.9464888148603581,"tier":"B"},{"sku":"S-AGPA8-1-LB","productName":"San Diego Bentgrass","category":"CA Collection","units":32,"lbs":32,"orders":7,"unitPrice":94.85,"revenue":3035.31,"unitCost":37.43,"totalCost":1197.78,"margin":1837.53,"marginPct":0.6053846229874379,"isNewSku":true,"hasPrice":true,"source":"fishbowl","costSource":"fishbowl","revenuePct":0.002666810639232921,"cumulativeRevenuePct":0.949155625499591,"tier":"B"},{"sku":"WB-FLN-0.5-LB","productName":"Florida Native Wildflower Mix","category":"FL Collection","units":255,"lbs":127.5,"orders":70,"unitPrice":11.89,"revenue":3032.56,"unitCost":5.47,"totalCost":1394.84,"margin":1637.72,"marginPct":0.540045374205292,"isNewSku":true,"hasPrice":true,"source":"fishbowl","costSource":"fishbowl","revenuePct":0.00266439450076341,"cumulativeRevenuePct":0.9518200200003544,"tier":"B"},{"sku":"PG-BUCK-5-LB","productName":"Buckwheat","category":"Pasture","units":82,"lbs":410,"orders":12,"unitPrice":34.45,"revenue":2825.05,"unitCost":1.75,"totalCost":143.5,"margin":2681.55,"marginPct":0.9492044388594892,"isNewSku":true,"hasPrice":true,"source":"fishbowl","costSource":"fishbowl","revenuePct":0.0024820770848331683,"cumulativeRevenuePct":0.9543020970851875,"tier":"C"},{"sku":"W-ACLA-0.25-LB","productName":"Western Yarrow","category":"CA Collection","units":175,"lbs":43.75,"orders":23,"unitPrice":15.86,"revenue":2775.46,"unitCost":1.96,"totalCost":342.53,"margin":2432.93,"marginPct":0.8765862235449258,"isNewSku":true,"hasPrice":true,"source":"fishbowl","costSource":"fishbowl","revenuePct":0.0024385075187593366,"cumulativeRevenuePct":0.9567406046039468,"tier":"C"},{"sku":"W-ASFA-0.25-LB","productName":"Narrowleaf Milkweed","category":"CA Collection","units":33,"lbs":8.25,"orders":6,"unitPrice":83.93,"revenue":2769.83,"unitCost":20.18,"totalCost":665.94,"margin":2103.89,"marginPct":0.7595736922482607,"isNewSku":true,"hasPrice":true,"source":"fishbowl","costSource":"fishbowl","revenuePct":0.002433561024365393,"cumulativeRevenuePct":0.9591741656283123,"tier":"C"},{"sku":"PB-SHEP-N-10-LB","productName":"Northern Sheep Forage Mix","category":"Pasture","units":65,"lbs":650,"orders":28,"unitPrice":41.96,"revenue":2727.22,"unitCost":0,"totalCost":0,"margin":2727.22,"marginPct":1,"isNewSku":true,"hasPrice":true,"source":"db","costSource":"none","revenuePct":0.0023961240570250834,"cumulativeRevenuePct":0.9615702896853373,"tier":"C"},{"sku":"PB-COSS-0.5-LB","productName":"Coastal Sage Scrub Mix","category":"CA Collection","units":81,"lbs":40.5,"orders":7,"unitPrice":32.84,"revenue":2659.76,"unitCost":7.67,"totalCost":621.54,"margin":2038.22,"marginPct":0.7663172617078232,"isNewSku":true,"hasPrice":true,"source":"fishbowl","costSource":"fishbowl","revenuePct":0.0023368539838784686,"cumulativeRevenuePct":0.9639071436692158,"tier":"C"},{"sku":"PB-IR-10-LB","productName":"Premium Irrigated Pasture Mix","category":"Pasture","units":76,"lbs":760,"orders":9,"unitPrice":34.76,"revenue":2642.09,"unitCost":16.29,"totalCost":1237.94,"margin":1404.15,"marginPct":0.5314542653732461,"isNewSku":true,"hasPrice":true,"source":"fishbowl","costSource":"fishbowl","revenuePct":0.0023213291959671032,"cumulativeRevenuePct":0.9662284728651829,"tier":"C"},{"sku":"WB-JPW-0.5-LB","productName":"Jimmy's Perennial Wildflower Mix","category":"Wildflowers","units":80,"lbs":40,"orders":20,"unitPrice":32.82,"revenue":2625.58,"unitCost":5.99,"totalCost":479.53,"margin":2146.05,"marginPct":0.8173622590056293,"isNewSku":true,"hasPrice":true,"source":"fishbowl","costSource":"fishbowl","revenuePct":0.0023068235791919678,"cumulativeRevenuePct":0.9685352964443749,"tier":"C"},{"sku":"PB-SHADE-10-LB","productName":"Shade Mix Food Plot","category":"Food Plot","units":26,"lbs":260,"orders":7,"unitPrice":93.66,"revenue":2435.22,"unitCost":4.58,"totalCost":119.08,"margin":2316.14,"marginPct":0.9511009272262876,"isNewSku":true,"hasPrice":true,"source":"fishbowl","costSource":"fishbowl","revenuePct":0.0021395740813534014,"cumulativeRevenuePct":0.9706748705257282,"tier":"C"},{"sku":"PB-BIRD-10-LB","productName":"Duck Kandy(Upland game Mix)","category":"Food Plot","units":81,"lbs":810,"orders":3,"unitPrice":29.46,"revenue":2386.56,"unitCost":7.91,"totalCost":640.92,"margin":1745.64,"marginPct":0.731446098149638,"isNewSku":true,"hasPrice":true,"source":"fishbowl","costSource":"fishbowl","revenuePct":0.0020968216093801687,"cumulativeRevenuePct":0.9727716921351084,"tier":"C"},{"sku":"PB-SHEP-SO-10-LB","productName":"Southern Sheep Forage Mix","category":"Pasture","units":40,"lbs":400,"orders":16,"unitPrice":58.53,"revenue":2341.31,"unitCost":0,"totalCost":0,"margin":2341.31,"marginPct":1,"isNewSku":true,"hasPrice":true,"source":"db","costSource":"none","revenuePct":0.002057065149109129,"cumulativeRevenuePct":0.9748287572842175,"tier":"C"},{"sku":"PG-TRHY-5-LB","productName":"Alsike Clover","category":"Lawn Alt","units":74,"lbs":370,"orders":15,"unitPrice":23.87,"revenue":1766.56,"unitCost":10.2,"totalCost":754.8,"margin":1011.76,"marginPct":0.5727289194819309,"isNewSku":true,"hasPrice":true,"source":"fishbowl","costSource":"fishbowl","revenuePct":0.0015520922089813918,"cumulativeRevenuePct":0.9763808494931988,"tier":"C"},{"sku":"PB-KRMU-10-LB","productName":"Krunch and Munch Food Plot","category":"Food Plot","units":57,"lbs":570,"orders":8,"unitPrice":29.55,"revenue":1684.19,"unitCost":5.79,"totalCost":329.78,"margin":1354.41,"marginPct":0.8041907385746264,"isNewSku":true,"hasPrice":true,"source":"fishbowl","costSource":"fishbowl","revenuePct":0.0014797222723509933,"cumulativeRevenuePct":0.9778605717655499,"tier":"C"},{"sku":"W-ENCA-0.25-LB","productName":"California Bush Sunflower","category":"CA Collection","units":76,"lbs":19,"orders":8,"unitPrice":22.13,"revenue":1681.76,"unitCost":7.77,"totalCost":590.4,"margin":1091.36,"marginPct":0.6489392065455237,"isNewSku":true,"hasPrice":true,"source":"fishbowl","costSource":"fishbowl","revenuePct":0.0014775872845397527,"cumulativeRevenuePct":0.9793381590500896,"tier":"C"},{"sku":"WB-FLPB-0.5-LB","productName":"Florida Pollinator Wildflower Mix","category":"FL Collection","units":97,"lbs":48.5,"orders":22,"unitPrice":17.32,"revenue":1679.94,"unitCost":7.64,"totalCost":741.48,"margin":938.46,"marginPct":0.5586270938247795,"isNewSku":true,"hasPrice":true,"source":"fishbowl","costSource":"fishbowl","revenuePct":0.0014759882401708404,"cumulativeRevenuePct":0.9808141472902604,"tier":"C"},{"sku":"PB-CLV-10-LB","productName":"Pasture Clover Mix (Clover Kandy) - Duck/Quail Food Plot","category":"Food Plot","units":41,"lbs":410,"orders":13,"unitPrice":36.55,"revenue":1498.59,"unitCost":25.25,"totalCost":1035.17,"margin":463.42,"marginPct":0.30923734977545564,"isNewSku":true,"hasPrice":true,"source":"fishbowl","costSource":"fishbowl","revenuePct":0.0013166548905541979,"cumulativeRevenuePct":0.9821308021808146,"tier":"C"},{"sku":"W-LUMI-0.25-LB","productName":"Chick Lupine","category":"CA Collection","units":59,"lbs":14.75,"orders":14,"unitPrice":24.44,"revenue":1441.78,"unitCost":3.21,"totalCost":189.41,"margin":1252.37,"marginPct":0.8686276685763431,"isNewSku":true,"hasPrice":true,"source":"fishbowl","costSource":"fishbowl","revenuePct":0.0012667418627531424,"cumulativeRevenuePct":0.9833975440435677,"tier":"C"},{"sku":"2750AL-A","productName":"Shoulder Strap Broadcast Seed Spreader","category":"Planting Aide","units":15,"lbs":0,"orders":4,"unitPrice":89.99,"revenue":1349.85,"unitCost":42.73,"totalCost":640.95,"margin":708.9,"marginPct":0.5251694632736971,"isNewSku":true,"hasPrice":true,"source":"fishbowl","costSource":"fishbowl","revenuePct":0.0011859725502069173,"cumulativeRevenuePct":0.9845835165937746,"tier":"C"},{"sku":"WB-FLCO-0.5-LB","productName":"Florida Coastal Native Wildflower Mix","category":"FL Collection","units":119,"lbs":59.5,"orders":35,"unitPrice":10.99,"revenue":1308.11,"unitCost":5.14,"totalCost":611.3,"margin":696.81,"marginPct":0.5326845601669584,"isNewSku":true,"hasPrice":true,"source":"fishbowl","costSource":"fishbowl","revenuePct":0.0011492999612187802,"cumulativeRevenuePct":0.9857328165549935,"tier":"C"},{"sku":"W-LUSU-0.25-LB","productName":"Arroyo Lupine","category":"CA Collection","units":89,"lbs":22.25,"orders":17,"unitPrice":14.51,"revenue":1291.38,"unitCost":3.14,"totalCost":279.74,"margin":1011.64,"marginPct":0.7833790208923787,"isNewSku":true,"hasPrice":true,"source":"fishbowl","costSource":"fishbowl","revenuePct":0.0011346010533660844,"cumulativeRevenuePct":0.9868674176083595,"tier":"C"},{"sku":"W-SIBE-0.25-LB","productName":"Blue-Eyed Grass","category":"CA Collection","units":32,"lbs":8,"orders":6,"unitPrice":39.68,"revenue":1269.7,"unitCost":3.69,"totalCost":118.12,"margin":1151.58,"marginPct":0.9069701504292351,"isNewSku":true,"hasPrice":true,"source":"fishbowl","costSource":"fishbowl","revenuePct":0.001115553096268269,"cumulativeRevenuePct":0.9879829707046278,"tier":"C"},{"sku":"PB-SOLS-10-LB","productName":"Southern Livestock Pasture and Forage Mix","category":"Pasture","units":26,"lbs":260,"orders":7,"unitPrice":46.95,"revenue":1220.76,"unitCost":23.01,"totalCost":598.35,"margin":622.41,"marginPct":0.5098545168583505,"isNewSku":true,"hasPrice":true,"source":"fishbowl","costSource":"fishbowl","revenuePct":0.0010725546174690495,"cumulativeRevenuePct":0.9890555253220968,"tier":"C"},{"sku":"WB-TEXN-0.5-LB","productName":"Texas Native Wildflower Mix","category":"TX Collection","units":38,"lbs":19,"orders":11,"unitPrice":29.95,"revenue":1137.91,"unitCost":12.09,"totalCost":459.59,"margin":678.32,"marginPct":0.5961104129500575,"isNewSku":true,"hasPrice":true,"source":"fishbowl","costSource":"fishbowl","revenuePct":0.0009997629548512453,"cumulativeRevenuePct":0.9900552882769481,"tier":"C"},{"sku":"PG-BOGR-5-LB","productName":"Blue Grama","category":"Pasture","units":3,"lbs":15,"orders":3,"unitPrice":325.87,"revenue":977.61,"unitCost":55.4,"totalCost":166.2,"margin":811.41,"marginPct":0.8299935557124006,"isNewSku":true,"hasPrice":true,"source":"fishbowl","costSource":"fishbowl","revenuePct":0.0008589240469739486,"cumulativeRevenuePct":0.9909142123239221,"tier":"C"},{"sku":"SUSTANE-18-1-8+FE","productName":"Organic Maintenance Fertilizer 18-1-8+fe","category":"Planting Aide","units":7,"lbs":280,"orders":1,"unitPrice":132.85,"revenue":929.94,"unitCost":55,"totalCost":385,"margin":544.94,"marginPct":0.5859947953631417,"isNewSku":true,"hasPrice":true,"source":"fishbowl","costSource":"fishbowl","revenuePct":0.0008170413848497394,"cumulativeRevenuePct":0.9917312537087718,"tier":"C"},{"sku":"PB-MUST-10-LB","productName":"Mustard Biofumigant Blend (cover crop)","category":"Planting Aide","units":23,"lbs":230,"orders":4,"unitPrice":38.82,"revenue":892.81,"unitCost":9.95,"totalCost":228.85,"margin":663.96,"marginPct":0.7436744660118055,"isNewSku":true,"hasPrice":true,"source":"fishbowl","costSource":"fishbowl","revenuePct":0.0007844191225323093,"cumulativeRevenuePct":0.9925156728313042,"tier":"C"},{"sku":"W-SAAP-0.25-LB","productName":"White Sage","category":"CA Collection","units":30,"lbs":7.5,"orders":12,"unitPrice":26.77,"revenue":803.06,"unitCost":8.31,"totalCost":249.19,"margin":553.87,"marginPct":0.6896993997957812,"isNewSku":true,"hasPrice":true,"source":"fishbowl","costSource":"fishbowl","revenuePct":0.0007055651488455509,"cumulativeRevenuePct":0.9932212379801497,"tier":"C"},{"sku":"PB-CABIN-5-LB","productName":"Native Cabin Grass Mix","category":"Pasture","units":19,"lbs":95,"orders":3,"unitPrice":39.13,"revenue":743.46,"unitCost":16.3,"totalCost":309.77,"margin":433.69,"marginPct":0.5833400586447152,"isNewSku":true,"hasPrice":true,"source":"fishbowl","costSource":"fishbowl","revenuePct":0.0006532008387427009,"cumulativeRevenuePct":0.9938744388188924,"tier":"C"},{"sku":"PB-FULL-10-LB","productName":"Full Potential Food Plot","category":"Food Plot","units":9,"lbs":90,"orders":2,"unitPrice":80.07,"revenue":720.66,"unitCost":27.46,"totalCost":247.15,"margin":473.51,"marginPct":0.6570504815030667,"isNewSku":true,"hasPrice":true,"source":"fishbowl","costSource":"fishbowl","revenuePct":0.0006331688543409394,"cumulativeRevenuePct":0.9945076076732333,"tier":"C"},{"sku":"W-DIAUA-0.25-LB","productName":"Monkeyflower","category":"CA Collection","units":38,"lbs":9.5,"orders":11,"unitPrice":18.92,"revenue":719.03,"unitCost":6.5,"totalCost":246.81,"margin":472.22,"marginPct":0.6567458937735561,"isNewSku":true,"hasPrice":true,"source":"fishbowl","costSource":"fishbowl","revenuePct":0.0006317367431753748,"cumulativeRevenuePct":0.9951393444164087,"tier":"C"},{"sku":"W-LUBI-0.25-LB","productName":"Miniature Lupine","category":"CA Collection","units":35,"lbs":8.75,"orders":9,"unitPrice":19.07,"revenue":667.36,"unitCost":7.71,"totalCost":269.77,"margin":397.59,"marginPct":0.5957654039798609,"isNewSku":true,"hasPrice":true,"source":"fishbowl","costSource":"fishbowl","revenuePct":0.0005863396978227865,"cumulativeRevenuePct":0.9957256841142315,"tier":"C"},{"sku":"W-NAPU-0.25-LB","productName":"Purple Needlegrass","category":"CA Collection","units":38,"lbs":9.5,"orders":6,"unitPrice":16.87,"revenue":641.09,"unitCost":3.33,"totalCost":126.36,"margin":514.73,"marginPct":0.8028981890218222,"isNewSku":true,"hasPrice":true,"source":"fishbowl","costSource":"fishbowl","revenuePct":0.0005632589859704061,"cumulativeRevenuePct":0.9962889431002019,"tier":"C"},{"sku":"W-ENFA-0.25-LB","productName":"Brittlebush","category":"CA Collection","units":68,"lbs":17,"orders":7,"unitPrice":9.25,"revenue":628.9,"unitCost":1.66,"totalCost":112.7,"margin":516.2,"marginPct":0.8207982191127366,"isNewSku":true,"hasPrice":true,"source":"fishbowl","costSource":"fishbowl","revenuePct":0.0005525489030819204,"cumulativeRevenuePct":0.9968414920032838,"tier":"C"},{"sku":"PB-CHSS-0.5-LB","productName":"Chaparral Sage Scrub Mix","category":"CA Collection","units":19,"lbs":9.5,"orders":2,"unitPrice":32.87,"revenue":624.6,"unitCost":9.22,"totalCost":175.19,"margin":449.41,"marginPct":0.7195164905539545,"isNewSku":true,"hasPrice":true,"source":"fishbowl","costSource":"fishbowl","revenuePct":0.0005487709411114128,"cumulativeRevenuePct":0.9973902629443951,"tier":"C"},{"sku":"W-LUTE-0.25-LB","productName":"Texas Bluebonnet - 0.25lbs","category":"Wildflowers","units":18,"lbs":4.5,"orders":8,"unitPrice":33.42,"revenue":601.54,"unitCost":15.48,"totalCost":278.62,"margin":322.92,"marginPct":0.536822156465073,"isNewSku":true,"hasPrice":true,"source":"fishbowl","costSource":"fishbowl","revenuePct":0.0005285105217998066,"cumulativeRevenuePct":0.997918773466195,"tier":"C"},{"sku":"PB-PLPR-10-LB","productName":"Plains Prairie Mix","category":"Pasture","units":3,"lbs":30,"orders":2,"unitPrice":170.51,"revenue":511.54,"unitCost":61.54,"totalCost":184.62,"margin":326.92,"marginPct":0.6390898072487,"isNewSku":true,"hasPrice":true,"source":"fishbowl","costSource":"fishbowl","revenuePct":0.00044943689916127457,"cumulativeRevenuePct":0.9983682103653563,"tier":"C"},{"sku":"W-TRDA-0.25-LB","productName":"Fakahatchee Grass ( Eastern Gamagrass)","category":"Wildflowers","units":29,"lbs":7.25,"orders":5,"unitPrice":16,"revenue":464.14,"unitCost":7.66,"totalCost":222.07,"margin":242.07,"marginPct":0.5215452234239669,"isNewSku":true,"hasPrice":true,"source":"fishbowl","costSource":"fishbowl","revenuePct":0.000407791457904981,"cumulativeRevenuePct":0.9987760018232612,"tier":"C"},{"sku":"W-OESP-0.25-LB","productName":"Pink Evening Primrose - 0.25lbs","category":"Wildflowers","units":34,"lbs":8.5,"orders":12,"unitPrice":12.22,"revenue":415.61,"unitCost":5.43,"totalCost":184.48,"margin":231.13,"marginPct":0.5561223262192921,"isNewSku":true,"hasPrice":true,"source":"fishbowl","costSource":"fishbowl","revenuePct":0.0003651532033866703,"cumulativeRevenuePct":0.9991411550266479,"tier":"C"},{"sku":"W-PHDR-0.25-LB","productName":"Drummond Phlox - 0.25lbs","category":"Wildflowers","units":35,"lbs":8.75,"orders":9,"unitPrice":11.44,"revenue":400.56,"unitCost":4.16,"totalCost":145.5,"margin":255.06,"marginPct":0.6367585380467345,"isNewSku":true,"hasPrice":true,"source":"fishbowl","costSource":"fishbowl","revenuePct":0.00035193033648989354,"cumulativeRevenuePct":0.9994930853631379,"tier":"C"},{"sku":"W-ERCO-0.25-LB","productName":"Golden Yarrow","category":"CA Collection","units":7,"lbs":1.75,"orders":2,"unitPrice":45.85,"revenue":320.94,"unitCost":11.34,"totalCost":79.37,"margin":241.57,"marginPct":0.7526952078270082,"isNewSku":true,"hasPrice":true,"source":"fishbowl","costSource":"fishbowl","revenuePct":0.0002819765383290055,"cumulativeRevenuePct":0.9997750619014668,"tier":"C"},{"sku":"W-COLA-0.25-LB","productName":"Lanceleaf Tickseed (Coreopsis) - 0.25lbs","category":"Wildflowers","units":30,"lbs":7.5,"orders":7,"unitPrice":8.53,"revenue":256.02,"unitCost":1.19,"totalCost":35.7,"margin":220.32,"marginPct":0.8605577689243028,"isNewSku":true,"hasPrice":true,"source":"fishbowl","costSource":"fishbowl","revenuePct":0.00022493809853241098,"cumulativeRevenuePct":0.9999999999999992,"tier":"C"}]}